sopel_factoriomods/__init__.py
sopel_factoriomods-0.1.1.dist-info/COPYING
sopel_factoriomods-0.1.1.dist-info/METADATA
sopel_factoriomods-0.1.1.dist-info/WHEEL
sopel_factoriomods-0.1.1.dist-info/entry_points.txt
sopel_factoriomods-0.1.1.dist-info/top_level.txt
sopel_factoriomods-0.1.1.dist-info/RECORD
